pip2spack/__init__.py
pip2spack/actions/__init__.py
pip2spack/actions/action.py
pip2spack/actions/action_dispatcher.py
pip2spack/actions/version.py
pip2spack/actions/create/__init__.py
pip2spack/actions/create/create_action.py
pip2spack/actions/dowload/__init__.py
pip2spack/actions/dowload/download_action.py
pip2spack/actions/update/__init__.py
pip2spack/actions/update/update_action.py
pip2spack/core/__init__.py
pip2spack/core/package.py
pip2spack/core/pypi_package.py
pip2spack/core/spack_repository.py
pip2spack/core/verification.py
pip2spack/framework/__init__.py
pip2spack/framework/constants.py
pip2spack/framework/helpers.py
pip2spack/framework/messages.py
pip2spack/main/__init__.py
pip2spack/main/main.py
pip2spack/templates/__init__.py
pip2spack/templates/package.j2
tests/__init__.py
tests/pip2spack/__init__.py
tests/pip2spack/core/__init__.py
tests/pip2spack/core/conftest.py
tests/pip2spack/core/mocks.py
tests/pip2spack/core/test_pypi_package.py
tests/pip2spack/core/test_verification.py
pip2spack-1.4.1.dist-info/LICENSE
pip2spack-1.4.1.dist-info/METADATA
pip2spack-1.4.1.dist-info/WHEEL
pip2spack-1.4.1.dist-info/entry_points.txt
pip2spack-1.4.1.dist-info/top_level.txt
pip2spack-1.4.1.dist-info/RECORD
