Metadata-Version: 2.1
Name: pip2spack
Version: 1.4.1
Summary: Automatically create and update a spack package base on the pypi.org information
Home-page: https://github.com/NexSabre/pip2spack
Author: Nex Sabre
Author-email: nexsabre@protonmail.com
License: UNKNOWN
Platform: UNKNOWN
Classifier: Programming Language :: Python :: 3
Classifier: License :: OSI Approved :: MIT License
Classifier: Operating System :: OS Independent
Requires-Python: >=3.6
License-File: LICENSE
Requires-Dist: requests (==2.22.0)
Requires-Dist: jinja2 (==2.11.3)
Requires-Dist: dataclasses (==0.6)
Requires-Dist: markupsafe (==2.0.1)
